sparkxgb/__init__.py
sparkxgb/common.py
sparkxgb/util.py
sparkxgb/xgboost.py
sparkxgb-0.4.dist-info/METADATA
sparkxgb-0.4.dist-info/WHEEL
sparkxgb-0.4.dist-info/top_level.txt
sparkxgb-0.4.dist-info/RECORD
